htsg/__init__.py
htsg/__main__.py
htsg/htsg.py
htsg-1.0.0.dist-info/LICENSE
htsg-1.0.0.dist-info/METADATA
htsg-1.0.0.dist-info/WHEEL
htsg-1.0.0.dist-info/entry_points.txt
htsg-1.0.0.dist-info/top_level.txt
htsg-1.0.0.dist-info/RECORD
