Metadata-Version: 2.1
Name: htsg
Version: 1.0.0
Summary: Another SSG
Home-page: https://github.com/laddge/htsg
Author: Laddge
Author-email: dev.laddge@gmail.com
License: MIT
Platform: UNKNOWN
Requires-Dist: jinja2
Requires-Dist: toml
Requires-Dist: watchdog
